content_blocks/__init__.py
content_blocks/abstract_models.py
content_blocks/admin.py
content_blocks/admin_forms.py
content_blocks/apps.py
content_blocks/conf.py
content_blocks/fields.py
content_blocks/forms.py
content_blocks/models.py
content_blocks/signals.py
content_blocks/urls.py
content_blocks/views.py
content_blocks/widgets.py
content_blocks/management/__init__.py
content_blocks/management/commands/__init__.py
content_blocks/management/commands/export_content_block_templates.py
content_blocks/management/commands/import_content_block_templates.py
content_blocks/migrations/0001_initial.py
content_blocks/migrations/0002_alter_contentblock_css_class_and_more.py
content_blocks/migrations/0003_alter_contentblocktemplatefield_unique_together_and_more.py
content_blocks/migrations/0004_remove_contentblocktemplate_no_cache.py
content_blocks/migrations/0005_alter_contentblockcollection_options.py
content_blocks/migrations/0006_iframefield_contentblockfield_iframe.py
content_blocks/migrations/0007_contentblock_name_and_more.py
content_blocks/migrations/0008_auto_20231019_1729.py
content_blocks/migrations/0009_alter_contentblock_name.py
content_blocks/migrations/0010_alter_contentblockfield_text.py
content_blocks/migrations/__init__.py
content_blocks/services/__init__.py
content_blocks/services/content_block.py
content_blocks/services/content_block_template.py
content_blocks/static/content_blocks/.DS_Store
content_blocks/static/content_blocks/css/.DS_Store
content_blocks/static/content_blocks/css/content_block_template_admin.css
content_blocks/static/content_blocks/css/content_blocks.css
content_blocks/static/content_blocks/fontawesome/css/fontawesome.min.css
content_blocks/static/content_blocks/fontawesome/css/light.min.css
content_blocks/static/content_blocks/fontawesome/css/procompatibility.css
content_blocks/static/content_blocks/fontawesome/css/solid.min.css
content_blocks/static/content_blocks/fontawesome/css/thin.min.css
django_content_blocks-1.5.4.dist-info/LICENSE
django_content_blocks-1.5.4.dist-info/METADATA
django_content_blocks-1.5.4.dist-info/WHEEL
django_content_blocks-1.5.4.dist-info/dependency_links.txt
django_content_blocks-1.5.4.dist-info/top_level.txt
django_content_blocks-1.5.4.dist-info/RECORD
